amazon_paapi5/__init__.py
amazon_paapi5/client.py
amazon_paapi5/config.py
amazon_paapi5/exceptions.py
amazon_paapi5/monitoring.py
amazon_paapi5/resource_constants.py
amazon_paapi5/resources.py
amazon_paapi5/signature.py
amazon_paapi5/models/__init__.py
amazon_paapi5/models/get_browse_nodes.py
amazon_paapi5/models/get_items.py
amazon_paapi5/models/get_variations.py
amazon_paapi5/models/search_items.py
amazon_paapi5/models/offersv2/__init__.py
amazon_paapi5/models/offersv2/availability.py
amazon_paapi5/models/offersv2/condition.py
amazon_paapi5/models/offersv2/deal_details.py
amazon_paapi5/models/offersv2/loyalty_points.py
amazon_paapi5/models/offersv2/merchant_info.py
amazon_paapi5/models/offersv2/money.py
amazon_paapi5/models/offersv2/offer_listing.py
amazon_paapi5/models/offersv2/offersv2.py
amazon_paapi5/models/offersv2/price.py
amazon_paapi5/models/offersv2/saving_basis.py
amazon_paapi5/models/offersv2/savings.py
amazon_paapi5/utils/__init__.py
amazon_paapi5/utils/async_helper.py
amazon_paapi5/utils/cache.py
amazon_paapi5/utils/file_cache.py
amazon_paapi5/utils/throttling.py
amazon_paapi5_python_sdk-1.0.7.dist-info/licenses/LICENSE
amazon_paapi5_python_sdk-1.0.7.dist-info/licenses/NOTICE
amazon_paapi5_python_sdk-1.0.7.dist-info/METADATA
amazon_paapi5_python_sdk-1.0.7.dist-info/WHEEL
amazon_paapi5_python_sdk-1.0.7.dist-info/top_level.txt
amazon_paapi5_python_sdk-1.0.7.dist-info/RECORD
