Metadata-Version: 2.4
Name: amazon-paapi5-python-sdk
Version: 1.0.7
Summary: Amazon Product Advertising API v5 Python SDK (Most Advance SDK)
Home-page: https://github.com/rajpurohithitesh/amazon-paapi5-python-sdk
Author: Hitesh Rajpurohit
Classifier: Programming Language :: Python :: 3
Classifier: License :: OSI Approved :: Apache Software License
Classifier: Operating System :: OS Independent
Requires-Python: >=3.9
License-File: LICENSE
License-File: NOTICE
Requires-Dist: requests>=2.28.0
Requires-Dist: aiohttp>=3.9.0
Requires-Dist: cachetools>=5.0.0
Requires-Dist: cryptography>=3.4.8
Provides-Extra: redis
Requires-Dist: redis>=4.0.0; extra == "redis"
Provides-Extra: dev
Requires-Dist: pytest>=7.0.0; extra == "dev"
Requires-Dist: pytest-asyncio>=0.18.0; extra == "dev"
Dynamic: author
Dynamic: classifier
Dynamic: description
Dynamic: description-content-type
Dynamic: home-page
Dynamic: license-file
Dynamic: provides-extra
Dynamic: requires-dist
Dynamic: requires-python
Dynamic: summary
